Fortuna.cpython-311-darwin.so
fortuna-5.6.0.dist-info/licenses/LICENSE
fortuna-5.6.0.dist-info/METADATA
fortuna-5.6.0.dist-info/WHEEL
fortuna-5.6.0.dist-info/top_level.txt
fortuna-5.6.0.dist-info/RECORD
