Metadata-Version: 2.4
Name: Fortuna
Version: 5.6.0
Summary: High Performance Random Value Toolkit
Home-page: https://github.com/BrokenShell/Fortuna
Author: Robert Sharp
Author-email: webmaster@sharpdesigndigital.com
License: Free for non-commercial use
Keywords: Fortuna,High Performance Random Value Toolkit,Random Patterns,Data Perturbation,Game Dice,WeightedChoice,Random Value Generator,Gaussian Distribution,Linear Distribution,TruffleShuffle,FlexCat,Percent True,ZeroCool,QuantumMonty,Custom Distribution,Rarity Table,D20,Generative Modeling,Multithreading Aware Random Engine,bernoulli,binomial,negative_binomial,geometric,poisson,lognormal,exponential,gamma,weibull,extreme_value,chi_squared,cauchy,fisher_f,student_t,pareto,vonmises,triangular
Platform: Darwin
Platform: Linux
Platform: Windows
Classifier: Development Status :: 6 - Mature
Classifier: Programming Language :: Python :: 3.11
Classifier: Programming Language :: Cython
Classifier: Programming Language :: C++
Classifier: Operating System :: MacOS :: MacOS X
Classifier: Operating System :: POSIX :: Linux
Classifier: Operating System :: Microsoft :: Windows
Classifier: Topic :: Software Development :: Libraries :: Python Modules
Requires-Python: >=3.7
License-File: LICENSE
Provides-Extra: scope
Requires-Dist: MonkeyScope>=1.5.0; extra == "scope"
Dynamic: author
Dynamic: author-email
Dynamic: classifier
Dynamic: description
Dynamic: description-content-type
Dynamic: home-page
Dynamic: keywords
Dynamic: license
Dynamic: license-file
Dynamic: platform
Dynamic: provides-extra
Dynamic: requires-python
Dynamic: summary
